speedmem/___init__.py
speedmem/speedmem.py
speedmem-0.1.0.dist-info/licenses/LICENSE
speedmem-0.1.0.dist-info/METADATA
speedmem-0.1.0.dist-info/WHEEL
speedmem-0.1.0.dist-info/top_level.txt
speedmem-0.1.0.dist-info/RECORD
