Metadata-Version: 2.4
Name: speedmem
Version: 0.1.0
Summary: A lightweight library for fast memory read/write and Vulkan-based overlay windows on Windows 10/11 x64.
Author-email: SelfCode <selfcode.dev@gmail.com>
Project-URL: Homepage, https://github.com/SelfC0de
Project-URL: Repository, https://github.com/SelfC0de/speedmem
Project-URL: Documentation, https://github.com/SelfC0de/speedmem#readme
Keywords: memory,overlay,vulkan,windows,game-development
Classifier: Development Status :: 3 - Alpha
Classifier: Intended Audience :: Developers
Classifier: Operating System :: Microsoft :: Windows :: Windows 10
Classifier: Operating System :: Microsoft :: Windows :: Windows 11
Classifier: Programming Language :: Python :: 3
Classifier: Programming Language :: Python :: 3.8
Classifier: Programming Language :: Python :: 3.9
Classifier: Programming Language :: Python :: 3.10
Classifier: Programming Language :: Python :: 3.11
Classifier: Topic :: Software Development :: Libraries :: Python Modules
Classifier: Topic :: Games/Entertainment
Requires-Python: >=3.8
License-File: LICENSE
Requires-Dist: pywin32>=306
Requires-Dist: vulkan>=1.3.0.0
Dynamic: license-file
